fittie/__init__.py
fittie/fitfile/__init__.py
fittie/fitfile/crc.py
fittie/fitfile/data_message.py
fittie/fitfile/decode.py
fittie/fitfile/definition_message.py
fittie/fitfile/field_definitions.py
fittie/fitfile/field_description.py
fittie/fitfile/fitfile.py
fittie/fitfile/header.py
fittie/fitfile/records.py
fittie/fitfile/util.py
fittie/fitfile/profile/__init__.py
fittie/fitfile/profile/base_types.py
fittie/fitfile/profile/field_type.py
fittie/fitfile/profile/fit_types.py
fittie/fitfile/profile/mesg_nums.py
fittie/fitfile/profile/message_profile.py
fittie/fitfile/profile/messages.py
fittie/fitfile/profile/util.py
fittie/fitfile/utils/__init__.py
fittie/fitfile/utils/datastream.py
fittie/fitfile/utils/endianness.py
fittie/fitfile/utils/exceptions.py
fittie/utils/__init__.py
fittie/utils/enrich_data.py
fittie/utils/gear_change_data.py
fittie-0.10.0.dist-info/licenses/LICENSE
fittie-0.10.0.dist-info/METADATA
fittie-0.10.0.dist-info/WHEEL
fittie-0.10.0.dist-info/top_level.txt
fittie-0.10.0.dist-info/RECORD
