Metadata-Version: 2.4
Name: fittie
Version: 0.10.0
Summary: FIT file tool
Author: Marcel Blijleven
Maintainer: Marcel Blijleven
License: MIT License
Keywords: fit,fitfile,fitfile decode,decoding,garmin
Classifier: License :: OSI Approved :: MIT License
Classifier: Programming Language :: Python :: 3 :: Only
Classifier: Programming Language :: Python :: 3.10
Classifier: Programming Language :: Python :: 3.11
Classifier: Programming Language :: Python :: 3.12
Classifier: Programming Language :: Python :: 3.13
Requires-Python: >=3.10
License-File: LICENSE
Requires-Dist: pydantic>=2.10.6
Dynamic: license-file
